okite/__init__.py
okite/__main__.py
okite/utils.py
okite/worker.py
okite/rpc/__init__.py
okite/rpc/pickler.py
okite/rpc/rpc.py
okite/rpc/stream.py
okite/rpc/transport.py
okite/wrap/__init__.py
okite/wrap/client.py
okite/wrap/proxy.py
okite/wrap/server.py
okite-0.0.6.dist-info/LICENSE
okite-0.0.6.dist-info/METADATA
okite-0.0.6.dist-info/WHEEL
okite-0.0.6.dist-info/top_level.txt
okite-0.0.6.dist-info/RECORD
